{"score_num": "896763\u4eba\u8bc4\u4ef7", "score": "9.6", "movie_name": "\u8096\u7533\u514b\u7684\u6551\u8d4e", "ranking": "1"}
{"score_num": "645894\u4eba\u8bc4\u4ef7", "score": "9.5", "movie_name": "\u9738\u738b\u522b\u59ec", "ranking": "2"}
{"score_num": "854552\u4eba\u8bc4\u4ef7", "score": "9.4", "movie_name": "\u8fd9\u4e2a\u6740\u624b\u4e0d\u592a\u51b7", "ranking": "3"}
{"score_num": "727391\u4eba\u8bc4\u4ef7", "score": "9.4", "movie_name": "\u963f\u7518\u6b63\u4f20", "ranking": "4"}
{"score_num": "424573\u4eba\u8bc4\u4ef7", "score": "9.5", "movie_name": "\u7f8e\u4e3d\u4eba\u751f", "ranking": "5"}
{"score_num": "678404\u4eba\u8bc4\u4ef7", "score": "9.2", "movie_name": "\u5343\u4e0e\u5343\u5bfb", "ranking": "6"}
{"score_num": "390823\u4eba\u8bc4\u4ef7", "score": "9.4", "movie_name": "\u8f9b\u5fb7\u52d2\u7684\u540d\u5355", "ranking": "7"}
{"score_num": "669054\u4eba\u8bc4\u4ef7", "score": "9.2", "movie_name": "\u6cf0\u5766\u5c3c\u514b\u53f7", "ranking": "8"}
{"score_num": "778442\u4eba\u8bc4\u4ef7", "score": "9.2", "movie_name": "\u76d7\u68a6\u7a7a\u95f4", "ranking": "9"}
{"score_num": "508180\u4eba\u8bc4\u4ef7", "score": "9.3", "movie_name": "\u673a\u5668\u4eba\u603b\u52a8\u5458", "ranking": "10"}
{"score_num": "609388\u4eba\u8bc4\u4ef7", "score": "9.2", "movie_name": "\u6d77\u4e0a\u94a2\u7434\u5e08", "ranking": "11"}
{"score_num": "688307\u4eba\u8bc4\u4ef7", "score": "9.1", "movie_name": "\u4e09\u50bb\u5927\u95f9\u5b9d\u83b1\u575e", "ranking": "12"}
{"score_num": "466609\u4eba\u8bc4\u4ef7", "score": "9.2", "movie_name": "\u5fe0\u72ac\u516b\u516c\u7684\u6545\u4e8b", "ranking": "13"}
{"score_num": "462187\u4eba\u8bc4\u4ef7", "score": "9.2", "movie_name": "\u653e\u725b\u73ed\u7684\u6625\u5929", "ranking": "14"}
{"score_num": "499516\u4eba\u8bc4\u4ef7", "score": "9.2", "movie_name": "\u5927\u8bdd\u897f\u6e38\u4e4b\u5927\u5723\u5a36\u4eb2", "ranking": "15"}
{"score_num": "350469\u4eba\u8bc4\u4ef7", "score": "9.2", "movie_name": "\u6559\u7236", "ranking": "16"}
{"score_num": "427034\u4eba\u8bc4\u4ef7", "score": "9.1", "movie_name": "\u9f99\u732b", "ranking": "17"}
{"score_num": "466685\u4eba\u8bc4\u4ef7", "score": "9.1", "movie_name": "\u695a\u95e8\u7684\u4e16\u754c", "ranking": "18"}
{"score_num": "275764\u4eba\u8bc4\u4ef7", "score": "9.2", "movie_name": "\u4e71\u4e16\u4f73\u4eba", "ranking": "19"}
{"score_num": "314721\u4eba\u8bc4\u4ef7", "score": "9.1", "movie_name": "\u5929\u5802\u7535\u5f71\u9662", "ranking": "20"}
{"score_num": "373099\u4eba\u8bc4\u4ef7", "score": "9.1", "movie_name": "\u89e6\u4e0d\u53ef\u53ca", "ranking": "21"}
{"score_num": "549204\u4eba\u8bc4\u4ef7", "score": "8.9", "movie_name": "\u5f53\u5e78\u798f\u6765\u6572\u95e8", "ranking": "22"}
{"score_num": "260523\u4eba\u8bc4\u4ef7", "score": "9.2", "movie_name": "\u7194\u7089", "ranking": "23"}
{"score_num": "408428\u4eba\u8bc4\u4ef7", "score": "9.0", "movie_name": "\u65e0\u95f4\u9053", "ranking": "24"}
{"score_num": "409824\u4eba\u8bc4\u4ef7", "score": "9.0", "movie_name": "\u640f\u51fb\u4ff1\u4e50\u90e8", "ranking": "25"}
{"score_num": "174685\u4eba\u8bc4\u4ef7", "score": "9.4", "movie_name": "\u5341\u4e8c\u6012\u6c49", "ranking": "26"}
{"score_num": "495220\u4eba\u8bc4\u4ef7", "score": "9.1", "movie_name": "\u661f\u9645\u7a7f\u8d8a", "ranking": "27"}
{"score_num": "559340\u4eba\u8bc4\u4ef7", "score": "8.9", "movie_name": "\u6026\u7136\u5fc3\u52a8", "ranking": "28"}
{"score_num": "289236\u4eba\u8bc4\u4ef7", "score": "9.1", "movie_name": "\u6307\u73af\u738b3\uff1a\u738b\u8005\u65e0\u654c", "ranking": "29"}
{"score_num": "587773\u4eba\u8bc4\u4ef7", "score": "9.0", "movie_name": "\u5c11\u5e74\u6d3e\u7684\u5947\u5e7b\u6f02\u6d41", "ranking": "30"}
{"score_num": "338252\u4eba\u8bc4\u4ef7", "score": "9.0", "movie_name": "\u5929\u7a7a\u4e4b\u57ce", "ranking": "31"}
{"score_num": "232885\u4eba\u8bc4\u4ef7", "score": "9.2", "movie_name": "\u9b3c\u5b50\u6765\u4e86", "ranking": "32"}
{"score_num": "326907\u4eba\u8bc4\u4ef7", "score": "9.0", "movie_name": "\u8759\u8760\u4fa0\uff1a\u9ed1\u6697\u9a91\u58eb", "ranking": "33"}
{"score_num": "391448\u4eba\u8bc4\u4ef7", "score": "8.9", "movie_name": "\u7f57\u9a6c\u5047\u65e5", "ranking": "34"}
{"score_num": "272011\u4eba\u8bc4\u4ef7", "score": "9.1", "movie_name": "\u6d3b\u7740", "ranking": "35"}
{"score_num": "403538\u4eba\u8bc4\u4ef7", "score": "8.9", "movie_name": "\u5927\u8bdd\u897f\u6e38\u4e4b\u6708\u5149\u5b9d\u76d2", "ranking": "36"}
{"score_num": "276961\u4eba\u8bc4\u4ef7", "score": "9.0", "movie_name": "\u4e24\u6746\u5927\u70df\u67aa", "ranking": "37"}
{"score_num": "504201\u4eba\u8bc4\u4ef7", "score": "8.9", "movie_name": "\u98de\u5c4b\u73af\u6e38\u8bb0", "ranking": "38"}
{"score_num": "226075\u4eba\u8bc4\u4ef7", "score": "9.1", "movie_name": "\u7a83\u542c\u98ce\u66b4", "ranking": "39"}
{"score_num": "280707\u4eba\u8bc4\u4ef7", "score": "9.0", "movie_name": "\u98de\u8d8a\u75af\u4eba\u9662", "ranking": "40"}
{"score_num": "183463\u4eba\u8bc4\u4ef7", "score": "9.3", "movie_name": "\u6d77\u8c5a\u6e7e", "ranking": "41"}
{"score_num": "325296\u4eba\u8bc4\u4ef7", "score": "8.9", "movie_name": "\u95fb\u9999\u8bc6\u5973\u4eba", "ranking": "42"}
{"score_num": "420966\u4eba\u8bc4\u4ef7", "score": "8.8", "movie_name": "V\u5b57\u4ec7\u6740\u961f", "ranking": "43"}
{"score_num": "353041\u4eba\u8bc4\u4ef7", "score": "8.9", "movie_name": "\u54c8\u5c14\u7684\u79fb\u52a8\u57ce\u5821", "ranking": "44"}
{"score_num": "89536\u4eba\u8bc4\u4ef7", "score": "9.6", "movie_name": "\u63a7\u65b9\u8bc1\u4eba", "ranking": "45"}
{"score_num": "188659\u4eba\u8bc4\u4ef7", "score": "9.1", "movie_name": "\u6559\u72362", "ranking": "46"}
{"score_num": "307529\u4eba\u8bc4\u4ef7", "score": "8.9", "movie_name": "\u7f8e\u4e3d\u5fc3\u7075", "ranking": "47"}
{"score_num": "272804\u4eba\u8bc4\u4ef7", "score": "8.9", "movie_name": "\u6307\u73af\u738b2\uff1a\u53cc\u5854\u5947\u5175", "ranking": "48"}
{"score_num": "280179\u4eba\u8bc4\u4ef7", "score": "8.9", "movie_name": "\u6b7b\u4ea1\u8bd7\u793e", "ranking": "49"}
{"score_num": "304898\u4eba\u8bc4\u4ef7", "score": "8.9", "movie_name": "\u6307\u73af\u738b1\uff1a\u9b54\u6212\u518d\u73b0", "ranking": "50"}
{"score_num": "377674\u4eba\u8bc4\u4ef7", "score": "8.8", "movie_name": "\u60c5\u4e66", "ranking": "51"}
{"score_num": "205579\u4eba\u8bc4\u4ef7", "score": "9.1", "movie_name": "\u8fa9\u62a4\u4eba", "ranking": "52"}
{"score_num": "484979\u4eba\u8bc4\u4ef7", "score": "8.7", "movie_name": "\u5929\u4f7f\u7231\u7f8e\u4e3d", "ranking": "53"}
{"score_num": "175739\u4eba\u8bc4\u4ef7", "score": "9.1", "movie_name": "\u7f8e\u56fd\u5f80\u4e8b", "ranking": "54"}
{"score_num": "198752\u4eba\u8bc4\u4ef7", "score": "9.0", "movie_name": "\u996e\u98df\u7537\u5973", "ranking": "55"}
{"score_num": "203909\u4eba\u8bc4\u4ef7", "score": "9.0", "movie_name": "\u94a2\u7434\u5bb6", "ranking": "56"}
{"score_num": "282823\u4eba\u8bc4\u4ef7", "score": "8.9", "movie_name": "\u72ee\u5b50\u738b", "ranking": "57"}
{"score_num": "437235\u4eba\u8bc4\u4ef7", "score": "8.7", "movie_name": "\u4e03\u5b97\u7f6a", "ranking": "58"}
{"score_num": "498950\u4eba\u8bc4\u4ef7", "score": "9.2", "movie_name": "\u75af\u72c2\u52a8\u7269\u57ce", "ranking": "59"}
{"score_num": "283793\u4eba\u8bc4\u4ef7", "score": "8.9", "movie_name": "\u88ab\u5acc\u5f03\u7684\u677e\u5b50\u7684\u4e00\u751f", "ranking": "60"}
{"score_num": "344807\u4eba\u8bc4\u4ef7", "score": "8.8", "movie_name": "\u81f4\u547d\u9b54\u672f", "ranking": "61"}
{"score_num": "137230\u4eba\u8bc4\u4ef7", "score": "9.2", "movie_name": "\u5c0f\u978b\u5b50", "ranking": "62"}
{"score_num": "296243\u4eba\u8bc4\u4ef7", "score": "8.8", "movie_name": "\u52c7\u6562\u7684\u5fc3", "ranking": "63"}
{"score_num": "485018\u4eba\u8bc4\u4ef7", "score": "8.7", "movie_name": "\u526a\u5200\u624b\u7231\u5fb7\u534e", "ranking": "64"}
{"score_num": "232334\u4eba\u8bc4\u4ef7", "score": "8.9", "movie_name": "\u97f3\u4e50\u4e4b\u58f0", "ranking": "65"}
{"score_num": "334795\u4eba\u8bc4\u4ef7", "score": "8.8", "movie_name": "\u4f4e\u4fd7\u5c0f\u8bf4", "ranking": "66"}
{"score_num": "177117\u4eba\u8bc4\u4ef7", "score": "9.1", "movie_name": "\u7d20\u5a9b", "ranking": "67"}
{"score_num": "393610\u4eba\u8bc4\u4ef7", "score": "8.7", "movie_name": "\u672c\u6770\u660e\u00b7\u5df4\u987f\u5947\u4e8b", "ranking": "68"}
{"score_num": "318935\u4eba\u8bc4\u4ef7", "score": "8.8", "movie_name": "\u5165\u6b93\u5e08", "ranking": "69"}
{"score_num": "280637\u4eba\u8bc4\u4ef7", "score": "8.8", "movie_name": "\u9ed1\u5ba2\u5e1d\u56fd", "ranking": "70"}
{"score_num": "353283\u4eba\u8bc4\u4ef7", "score": "8.7", "movie_name": "\u6c89\u9ed8\u7684\u7f94\u7f8a", "ranking": "71"}
{"score_num": "237218\u4eba\u8bc4\u4ef7", "score": "8.8", "movie_name": "\u62ef\u6551\u5927\u5175\u745e\u6069", "ranking": "72"}
{"score_num": "346929\u4eba\u8bc4\u4ef7", "score": "8.7", "movie_name": "\u897f\u897f\u91cc\u7684\u7f8e\u4e3d\u4f20\u8bf4", "ranking": "73"}
{"score_num": "232286\u4eba\u8bc4\u4ef7", "score": "8.9", "movie_name": "\u739b\u4e3d\u548c\u9a6c\u514b\u601d", "ranking": "74"}
{"score_num": "381141\u4eba\u8bc4\u4ef7", "score": "8.7", "movie_name": "\u8774\u8776\u6548\u5e94", "ranking": "75"}
{"score_num": "244809\u4eba\u8bc4\u4ef7", "score": "8.8", "movie_name": "\u6625\u5149\u4e4d\u6cc4", "ranking": "76"}
{"score_num": "620767\u4eba\u8bc4\u4ef7", "score": "8.7", "movie_name": "\u8ba9\u5b50\u5f39\u98de", "ranking": "77"}
{"score_num": "269581\u4eba\u8bc4\u4ef7", "score": "8.7", "movie_name": "\u5fc3\u7075\u6355\u624b", "ranking": "78"}
{"score_num": "233802\u4eba\u8bc4\u4ef7", "score": "8.8", "movie_name": "\u5e7d\u7075\u516c\u4e3b", "ranking": "79"}
{"score_num": "97900\u4eba\u8bc4\u4ef7", "score": "9.2", "movie_name": "\u5927\u95f9\u5929\u5bab", "ranking": "80"}
{"score_num": "268847\u4eba\u8bc4\u4ef7", "score": "8.7", "movie_name": "\u9633\u5149\u707f\u70c2\u7684\u65e5\u5b50", "ranking": "81"}
{"score_num": "234058\u4eba\u8bc4\u4ef7", "score": "8.8", "movie_name": "\u7b2c\u516d\u611f", "ranking": "82"}
{"score_num": "327746\u4eba\u8bc4\u4ef7", "score": "8.6", "movie_name": "\u91cd\u5e86\u68ee\u6797", "ranking": "83"}
{"score_num": "251060\u4eba\u8bc4\u4ef7", "score": "8.7", "movie_name": "\u5927\u9c7c", "ranking": "84"}
{"score_num": "274388\u4eba\u8bc4\u4ef7", "score": "8.7", "movie_name": "\u5c04\u96d5\u82f1\u96c4\u4f20\u4e4b\u4e1c\u6210\u897f\u5c31", "ranking": "85"}
{"score_num": "356751\u4eba\u8bc4\u4ef7", "score": "8.6", "movie_name": "\u7981\u95ed\u5c9b", "ranking": "86"}
{"score_num": "231238\u4eba\u8bc4\u4ef7", "score": "8.7", "movie_name": "\u751c\u871c\u871c", "ranking": "87"}
{"score_num": "266598\u4eba\u8bc4\u4ef7", "score": "8.8", "movie_name": "\u9633\u5149\u59d0\u59b9\u6dd8", "ranking": "88"}
{"score_num": "157352\u4eba\u8bc4\u4ef7", "score": "8.9", "movie_name": "\u4e0a\u5e1d\u4e4b\u57ce", "ranking": "89"}
{"score_num": "154694\u4eba\u8bc4\u4ef7", "score": "8.9", "movie_name": "\u4e00\u4e00", "ranking": "90"}
{"score_num": "316056\u4eba\u8bc4\u4ef7", "score": "8.6", "movie_name": "\u81f4\u547dID", "ranking": "91"}
{"score_num": "125634\u4eba\u8bc4\u4ef7", "score": "9.0", "movie_name": "\u72e9\u730e", "ranking": "92"}
{"score_num": "339665\u4eba\u8bc4\u4ef7", "score": "8.7", "movie_name": "\u544a\u767d", "ranking": "93"}
{"score_num": "162417\u4eba\u8bc4\u4ef7", "score": "8.9", "movie_name": "\u672b\u4ee3\u7687\u5e1d", "ranking": "94"}
{"score_num": "304847\u4eba\u8bc4\u4ef7", "score": "8.7", "movie_name": "\u5e03\u8fbe\u4f69\u65af\u5927\u996d\u5e97", "ranking": "95"}
{"score_num": "340255\u4eba\u8bc4\u4ef7", "score": "8.6", "movie_name": "\u52a0\u52d2\u6bd4\u6d77\u76d7", "ranking": "96"}
{"score_num": "315386\u4eba\u8bc4\u4ef7", "score": "8.6", "movie_name": "\u65ad\u80cc\u5c71", "ranking": "97"}
{"score_num": "217688\u4eba\u8bc4\u4ef7", "score": "8.7", "movie_name": "\u7231\u5728\u9ece\u660e\u7834\u6653\u524d", "ranking": "98"}
{"score_num": "87003\u4eba\u8bc4\u4ef7", "score": "9.2", "movie_name": "\u6469\u767b\u65f6\u4ee3", "ranking": "99"}
{"score_num": "523872\u4eba\u8bc4\u4ef7", "score": "8.6", "movie_name": "\u963f\u51e1\u8fbe", "ranking": "100"}
{"score_num": "219954\u4eba\u8bc4\u4ef7", "score": "8.7", "movie_name": "\u732b\u9f20\u6e38\u620f", "ranking": "101"}
{"score_num": "249338\u4eba\u8bc4\u4ef7", "score": "8.7", "movie_name": "\u54c8\u5229\u00b7\u6ce2\u7279\u4e0e\u9b54\u6cd5\u77f3", "ranking": "102"}
{"score_num": "174241\u4eba\u8bc4\u4ef7", "score": "8.8", "movie_name": "\u98ce\u4e4b\u8c37", "ranking": "103"}
{"score_num": "196305\u4eba\u8bc4\u4ef7", "score": "8.7", "movie_name": "\u7231\u5728\u65e5\u843d\u9ec4\u660f\u65f6", "ranking": "104"}
{"score_num": "165787\u4eba\u8bc4\u4ef7", "score": "8.8", "movie_name": "\u4fa7\u8033\u503e\u542c", "ranking": "105"}
{"score_num": "140575\u4eba\u8bc4\u4ef7", "score": "8.9", "movie_name": "\u7a7f\u6761\u7eb9\u7761\u8863\u7684\u7537\u5b69", "ranking": "106"}
{"score_num": "247133\u4eba\u8bc4\u4ef7", "score": "8.7", "movie_name": "\u770b\u4e0d\u89c1\u7684\u5ba2\u4eba", "ranking": "107"}
{"score_num": "201489\u4eba\u8bc4\u4ef7", "score": "8.7", "movie_name": "\u8424\u706b\u866b\u4e4b\u5893", "ranking": "108"}
{"score_num": "348159\u4eba\u8bc4\u4ef7", "score": "8.7", "movie_name": "\u6d88\u5931\u7684\u7231\u4eba", "ranking": "109"}
{"score_num": "170018\u4eba\u8bc4\u4ef7", "score": "8.8", "movie_name": "\u8d85\u8131", "ranking": "110"}
{"score_num": "280562\u4eba\u8bc4\u4ef7", "score": "8.7", "movie_name": "\u9a6f\u9f99\u9ad8\u624b", "ranking": "111"}
{"score_num": "178418\u4eba\u8bc4\u4ef7", "score": "8.7", "movie_name": "\u83ca\u6b21\u90ce\u7684\u590f\u5929", "ranking": "112"}
{"score_num": "244970\u4eba\u8bc4\u4ef7", "score": "8.6", "movie_name": "\u5029\u5973\u5e7d\u9b42", "ranking": "113"}
{"score_num": "214128\u4eba\u8bc4\u4ef7", "score": "8.7", "movie_name": "\u6050\u6016\u76f4\u64ad", "ranking": "114"}
{"score_num": "222398\u4eba\u8bc4\u4ef7", "score": "8.6", "movie_name": "\u5e78\u798f\u7ec8\u70b9\u7ad9", "ranking": "115"}
{"score_num": "98229\u4eba\u8bc4\u4ef7", "score": "9.0", "movie_name": "\u6d77\u6d0b", "ranking": "116"}
{"score_num": "76119\u4eba\u8bc4\u4ef7", "score": "9.2", "movie_name": "\u4e03\u6b66\u58eb", "ranking": "117"}
{"score_num": "129706\u4eba\u8bc4\u4ef7", "score": "8.9", "movie_name": "\u7ea2\u8fa3\u6912", "ranking": "118"}
{"score_num": "303351\u4eba\u8bc4\u4ef7", "score": "8.6", "movie_name": "\u5c81\u6708\u795e\u5077", "ranking": "119"}
{"score_num": "368366\u4eba\u8bc4\u4ef7", "score": "8.5", "movie_name": "\u795e\u5077\u5976\u7238", "ranking": "120"}
{"score_num": "212851\u4eba\u8bc4\u4ef7", "score": "8.7", "movie_name": "\u501f\u4e1c\u897f\u7684\u5c0f\u4eba\u963f\u8389\u57c3\u8482", "ranking": "121"}
{"score_num": "177971\u4eba\u8bc4\u4ef7", "score": "8.7", "movie_name": "\u8c0d\u5f71\u91cd\u91cd3", "ranking": "122"}
{"score_num": "195940\u4eba\u8bc4\u4ef7", "score": "8.6", "movie_name": "\u7535\u952f\u60ca\u9b42", "ranking": "123"}
{"score_num": "206058\u4eba\u8bc4\u4ef7", "score": "8.6", "movie_name": "\u6740\u4eba\u56de\u5fc6", "ranking": "124"}
{"score_num": "303730\u4eba\u8bc4\u4ef7", "score": "8.5", "movie_name": "\u771f\u7231\u81f3\u4e0a", "ranking": "125"}
{"score_num": "147318\u4eba\u8bc4\u4ef7", "score": "8.7", "movie_name": "\u71c3\u60c5\u5c81\u6708", "ranking": "126"}
{"score_num": "207109\u4eba\u8bc4\u4ef7", "score": "8.6", "movie_name": "\u96e8\u4eba", "ranking": "127"}
{"score_num": "391102\u4eba\u8bc4\u4ef7", "score": "8.5", "movie_name": "\u8d2b\u6c11\u7a9f\u7684\u767e\u4e07\u5bcc\u7fc1", "ranking": "128"}
{"score_num": "245382\u4eba\u8bc4\u4ef7", "score": "8.6", "movie_name": "\u4e1c\u90aa\u897f\u6bd2", "ranking": "129"}
{"score_num": "274784\u4eba\u8bc4\u4ef7", "score": "8.5", "movie_name": "\u8bb0\u5fc6\u788e\u7247", "ranking": "130"}
{"score_num": "105647\u4eba\u8bc4\u4ef7", "score": "8.9", "movie_name": "\u864e\u53e3\u8131\u9669", "ranking": "131"}
{"score_num": "363940\u4eba\u8bc4\u4ef7", "score": "8.7", "movie_name": "\u75af\u72c2\u539f\u59cb\u4eba", "ranking": "132"}
{"score_num": "136177\u4eba\u8bc4\u4ef7", "score": "8.8", "movie_name": "\u559c\u5bb4", "ranking": "133"}
{"score_num": "234171\u4eba\u8bc4\u4ef7", "score": "8.6", "movie_name": "\u602a\u517d\u7535\u529b\u516c\u53f8", "ranking": "134"}
{"score_num": "124419\u4eba\u8bc4\u4ef7", "score": "8.9", "movie_name": "\u5c0f\u68ee\u6797 \u590f\u79cb\u7bc7", "ranking": "135"}
{"score_num": "303950\u4eba\u8bc4\u4ef7", "score": "8.5", "movie_name": "\u559c\u5267\u4e4b\u738b", "ranking": "136"}
{"score_num": "116854\u4eba\u8bc4\u4ef7", "score": "8.8", "movie_name": "\u5362\u65fa\u8fbe\u996d\u5e97", "ranking": "137"}
{"score_num": "409713\u4eba\u8bc4\u4ef7", "score": "8.5", "movie_name": "\u9ed1\u5929\u9e45", "ranking": "138"}
{"score_num": "146833\u4eba\u8bc4\u4ef7", "score": "8.7", "movie_name": "\u82f1\u96c4\u672c\u8272", "ranking": "139"}
{"score_num": "244996\u4eba\u8bc4\u4ef7", "score": "8.5", "movie_name": "\u731c\u706b\u8f66", "ranking": "140"}
{"score_num": "182113\u4eba\u8bc4\u4ef7", "score": "8.6", "movie_name": "\u7a7f\u8d8a\u65f6\u7a7a\u7684\u5c11\u5973", "ranking": "141"}
{"score_num": "127218\u4eba\u8bc4\u4ef7", "score": "8.8", "movie_name": "\u9b42\u65ad\u84dd\u6865", "ranking": "142"}
{"score_num": "275269\u4eba\u8bc4\u4ef7", "score": "8.5", "movie_name": "\u604b\u604b\u7b14\u8bb0\u672c", "ranking": "143"}
{"score_num": "91471\u4eba\u8bc4\u4ef7", "score": "8.9", "movie_name": "\u96e8\u4e2d\u66f2", "ranking": "144"}
{"score_num": "294411\u4eba\u8bc4\u4ef7", "score": "8.4", "movie_name": "\u50b2\u6162\u4e0e\u504f\u89c1", "ranking": "145"}
{"score_num": "126544\u4eba\u8bc4\u4ef7", "score": "8.7", "movie_name": "\u6559\u72363", "ranking": "146"}
{"score_num": "77552\u4eba\u8bc4\u4ef7", "score": "9.0", "movie_name": "\u5b8c\u7f8e\u7684\u4e16\u754c", "ranking": "147"}
{"score_num": "140050\u4eba\u8bc4\u4ef7", "score": "8.7", "movie_name": "\u7eb5\u6a2a\u56db\u6d77", "ranking": "148"}
{"score_num": "152017\u4eba\u8bc4\u4ef7", "score": "8.7", "movie_name": "\u8424\u706b\u4e4b\u68ee", "ranking": "149"}
{"score_num": "188015\u4eba\u8bc4\u4ef7", "score": "8.8", "movie_name": "\u73a9\u5177\u603b\u52a8\u54583", "ranking": "150"}
{"score_num": "266543\u4eba\u8bc4\u4ef7", "score": "8.6", "movie_name": "\u54c8\u5229\u00b7\u6ce2\u7279\u4e0e\u6b7b\u4ea1\u5723\u5668(\u4e0b)", "ranking": "151"}
{"score_num": "240352\u4eba\u8bc4\u4ef7", "score": "8.5", "movie_name": "\u82b1\u6837\u5e74\u534e", "ranking": "152"}
{"score_num": "81822\u4eba\u8bc4\u4ef7", "score": "8.8", "movie_name": "\u4e8c\u5341\u4e8c", "ranking": "153"}
{"score_num": "168598\u4eba\u8bc4\u4ef7", "score": "8.6", "movie_name": "7\u53f7\u623f\u7684\u793c\u7269", "ranking": "154"}
{"score_num": "185627\u4eba\u8bc4\u4ef7", "score": "8.6", "movie_name": "\u4eba\u5de5\u667a\u80fd", "ranking": "155"}
{"score_num": "100065\u4eba\u8bc4\u4ef7", "score": "8.8", "movie_name": "\u6211\u662f\u5c71\u59c6", "ranking": "156"}
{"score_num": "128729\u4eba\u8bc4\u4ef7", "score": "8.7", "movie_name": "\u6d6a\u6f6e", "ranking": "157"}
{"score_num": "160378\u4eba\u8bc4\u4ef7", "score": "8.6", "movie_name": "\u6d77\u8fb9\u7684\u66fc\u5f7b\u65af\u7279", "ranking": "158"}
{"score_num": "129878\u4eba\u8bc4\u4ef7", "score": "8.7", "movie_name": "\u8352\u86ee\u6545\u4e8b", "ranking": "159"}
{"score_num": "269651\u4eba\u8bc4\u4ef7", "score": "8.4", "movie_name": "\u9999\u6c34", "ranking": "160"}
{"score_num": "263549\u4eba\u8bc4\u4ef7", "score": "8.4", "movie_name": "\u51b0\u5ddd\u65f6\u4ee3", "ranking": "161"}
{"score_num": "273055\u4eba\u8bc4\u4ef7", "score": "8.5", "movie_name": "\u6717\u8bfb\u8005", "ranking": "162"}
{"score_num": "79740\u4eba\u8bc4\u4ef7", "score": "8.9", "movie_name": "\u8ffd\u968f", "ranking": "163"}
{"score_num": "170728\u4eba\u8bc4\u4ef7", "score": "8.6", "movie_name": "\u649e\u8f66", "ranking": "164"}
{"score_num": "106786\u4eba\u8bc4\u4ef7", "score": "8.9", "movie_name": "\u5c0f\u68ee\u6797 \u51ac\u6625\u7bc7", "ranking": "165"}
{"score_num": "120824\u4eba\u8bc4\u4ef7", "score": "8.7", "movie_name": "\u7f57\u751f\u95e8", "ranking": "166"}
{"score_num": "128880\u4eba\u8bc4\u4ef7", "score": "8.7", "movie_name": "\u4e00\u6b21\u522b\u79bb", "ranking": "167"}
{"score_num": "191031\u4eba\u8bc4\u4ef7", "score": "8.6", "movie_name": "\u65f6\u7a7a\u604b\u65c5\u4eba", "ranking": "168"}
{"score_num": "153915\u4eba\u8bc4\u4ef7", "score": "8.6", "movie_name": "\u5fc3\u8ff7\u5bab", "ranking": "169"}
{"score_num": "311505\u4eba\u8bc4\u4ef7", "score": "8.4", "movie_name": "\u5510\u4f2f\u864e\u70b9\u79cb\u9999", "ranking": "170"}
{"score_num": "355733\u4eba\u8bc4\u4ef7", "score": "8.6", "movie_name": "\u8d85\u80fd\u9646\u6218\u961f", "ranking": "171"}
{"score_num": "286428\u4eba\u8bc4\u4ef7", "score": "8.5", "movie_name": "\u8759\u8760\u4fa0\uff1a\u9ed1\u6697\u9a91\u58eb\u5d1b\u8d77", "ranking": "172"}
{"score_num": "170522\u4eba\u8bc4\u4ef7", "score": "8.5", "movie_name": "\u6218\u4e89\u4e4b\u738b", "ranking": "173"}
{"score_num": "125471\u4eba\u8bc4\u4ef7", "score": "8.6", "movie_name": "\u53ef\u53ef\u897f\u91cc", "ranking": "174"}
{"score_num": "108985\u4eba\u8bc4\u4ef7", "score": "8.7", "movie_name": "\u68a6\u4e4b\u5b89\u9b42\u66f2", "ranking": "175"}
{"score_num": "81432\u4eba\u8bc4\u4ef7", "score": "8.8", "movie_name": "\u5730\u7403\u4e0a\u7684\u661f\u661f", "ranking": "176"}
{"score_num": "106231\u4eba\u8bc4\u4ef7", "score": "8.7", "movie_name": "\u78a7\u6d77\u84dd\u5929", "ranking": "177"}
{"score_num": "91927\u4eba\u8bc4\u4ef7", "score": "8.8", "movie_name": "\u672a\u9ebb\u7684\u90e8\u5c4b", "ranking": "178"}
{"score_num": "228838\u4eba\u8bc4\u4ef7", "score": "8.6", "movie_name": "\u7206\u88c2\u9f13\u624b", "ranking": "179"}
{"score_num": "285561\u4eba\u8bc4\u4ef7", "score": "8.3", "movie_name": "\u79d2\u901f5\u5398\u7c73", "ranking": "180"}
{"score_num": "309794\u4eba\u8bc4\u4ef7", "score": "8.3", "movie_name": "\u6050\u6016\u6e38\u8f6e", "ranking": "181"}
{"score_num": "154567\u4eba\u8bc4\u4ef7", "score": "8.5", "movie_name": "\u8c0d\u5f71\u91cd\u91cd2", "ranking": "182"}
{"score_num": "174797\u4eba\u8bc4\u4ef7", "score": "8.5", "movie_name": "\u963f\u98de\u6b63\u4f20", "ranking": "183"}
{"score_num": "186451\u4eba\u8bc4\u4ef7", "score": "8.5", "movie_name": "\u8c0d\u5f71\u91cd\u91cd", "ranking": "184"}
{"score_num": "162493\u4eba\u8bc4\u4ef7", "score": "8.6", "movie_name": "\u8fbe\u62c9\u65af\u4e70\u5bb6\u4ff1\u4e50\u90e8", "ranking": "185"}
{"score_num": "102603\u4eba\u8bc4\u4ef7", "score": "8.7", "movie_name": "\u726f\u5cad\u8857\u5c11\u5e74\u6740\u4eba\u4e8b\u4ef6", "ranking": "186"}
{"score_num": "162118\u4eba\u8bc4\u4ef7", "score": "8.6", "movie_name": "\u6d77\u76d7\u7535\u53f0", "ranking": "187"}
{"score_num": "79635\u4eba\u8bc4\u4ef7", "score": "8.8", "movie_name": "\u60ca\u9b42\u8bb0", "ranking": "188"}
{"score_num": "187415\u4eba\u8bc4\u4ef7", "score": "8.4", "movie_name": "\u9b54\u5973\u5b85\u6025\u4fbf", "ranking": "189"}
{"score_num": "251826\u4eba\u8bc4\u4ef7", "score": "8.5", "movie_name": "\u88ab\u89e3\u6551\u7684\u59dc\u6208", "ranking": "190"}
{"score_num": "160838\u4eba\u8bc4\u4ef7", "score": "8.5", "movie_name": "\u518d\u6b21\u51fa\u53d1\u4e4b\u7ebd\u7ea6\u9047\u89c1\u4f60", "ranking": "191"}
{"score_num": "48608\u4eba\u8bc4\u4ef7", "score": "9.2", "movie_name": "\u4e1c\u4eac\u7269\u8bed", "ranking": "192"}
{"score_num": "102997\u4eba\u8bc4\u4ef7", "score": "8.7", "movie_name": "\u7eff\u91cc\u5947\u8ff9", "ranking": "193"}
{"score_num": "138088\u4eba\u8bc4\u4ef7", "score": "8.5", "movie_name": "\u52c7\u95ef\u593a\u547d\u5c9b", "ranking": "194"}
{"score_num": "50755\u4eba\u8bc4\u4ef7", "score": "9.1", "movie_name": "\u8fc1\u5f99\u7684\u9e1f", "ranking": "195"}
{"score_num": "100869\u4eba\u8bc4\u4ef7", "score": "8.7", "movie_name": "\u672b\u8def\u72c2\u82b1", "ranking": "196"}
{"score_num": "212170\u4eba\u8bc4\u4ef7", "score": "8.4", "movie_name": "\u9752\u86c7", "ranking": "197"}
{"score_num": "123304\u4eba\u8bc4\u4ef7", "score": "8.6", "movie_name": "\u8352\u91ce\u751f\u5b58", "ranking": "198"}
{"score_num": "76820\u4eba\u8bc4\u4ef7", "score": "8.8", "movie_name": "\u54ea\u5412\u95f9\u6d77", "ranking": "199"}
{"score_num": "120711\u4eba\u8bc4\u4ef7", "score": "8.6", "movie_name": "\u5361\u8428\u5e03\u5170\u5361", "ranking": "200"}
{"score_num": "136329\u4eba\u8bc4\u4ef7", "score": "8.5", "movie_name": "\u7ec8\u7ed3\u80052\uff1a\u5ba1\u5224\u65e5", "ranking": "201"}
{"score_num": "54769\u4eba\u8bc4\u4ef7", "score": "9.0", "movie_name": "\u5fe0\u72ac\u516b\u516c\u7269\u8bed", "ranking": "202"}
{"score_num": "172253\u4eba\u8bc4\u4ef7", "score": "8.5", "movie_name": "\u8fd9\u4e2a\u7537\u4eba\u6765\u81ea\u5730\u7403", "ranking": "203"}
{"score_num": "105529\u4eba\u8bc4\u4ef7", "score": "8.6", "movie_name": "\u71d5\u5c3e\u8776", "ranking": "204"}
{"score_num": "207612\u4eba\u8bc4\u4ef7", "score": "8.4", "movie_name": "\u53d8\u8138", "ranking": "205"}
{"score_num": "396153\u4eba\u8bc4\u4ef7", "score": "8.3", "movie_name": "\u6e90\u4ee3\u7801", "ranking": "206"}
{"score_num": "176294\u4eba\u8bc4\u4ef7", "score": "8.4", "movie_name": "\u65b0\u9f99\u95e8\u5ba2\u6808", "ranking": "207"}
{"score_num": "169667\u4eba\u8bc4\u4ef7", "score": "8.4", "movie_name": "\u82f1\u56fd\u75c5\u4eba", "ranking": "208"}
{"score_num": "147451\u4eba\u8bc4\u4ef7", "score": "8.5", "movie_name": "E.T. \u5916\u661f\u4eba", "ranking": "209"}
{"score_num": "49467\u4eba\u8bc4\u4ef7", "score": "9.1", "movie_name": "\u9ec4\u91d1\u4e09\u9556\u5ba2", "ranking": "210"}
{"score_num": "149466\u4eba\u8bc4\u4ef7", "score": "8.5", "movie_name": "\u9ed1\u5ba2\u5e1d\u56fd3\uff1a\u77e9\u9635\u9769\u547d", "ranking": "211"}
{"score_num": "180520\u4eba\u8bc4\u4ef7", "score": "8.4", "movie_name": "\u53d1\u6761\u6a59", "ranking": "212"}
{"score_num": "41646\u4eba\u8bc4\u4ef7", "score": "9.2", "movie_name": "\u57ce\u5e02\u4e4b\u5149", "ranking": "213"}
{"score_num": "178915\u4eba\u8bc4\u4ef7", "score": "8.4", "movie_name": "\u7f8e\u56fd\u4e3d\u4eba", "ranking": "214"}
{"score_num": "105369\u4eba\u8bc4\u4ef7", "score": "8.6", "movie_name": "\u53eb\u6211\u7b2c\u4e00\u540d", "ranking": "215"}
{"score_num": "216182\u4eba\u8bc4\u4ef7", "score": "8.4", "movie_name": "\u65e0\u803b\u6df7\u86cb", "ranking": "216"}
{"score_num": "226978\u4eba\u8bc4\u4ef7", "score": "8.3", "movie_name": "\u7a46\u8d6b\u5170\u9053", "ranking": "217"}
{"score_num": "112144\u4eba\u8bc4\u4ef7", "score": "8.6", "movie_name": "\u975e\u5e38\u5acc\u7591\u72af", "ranking": "218"}
{"score_num": "442302\u4eba\u8bc4\u4ef7", "score": "8.2", "movie_name": "\u521d\u604b\u8fd9\u4ef6\u5c0f\u4e8b", "ranking": "219"}
{"score_num": "84980\u4eba\u8bc4\u4ef7", "score": "8.9", "movie_name": "\u52c7\u58eb", "ranking": "220"}
{"score_num": "243466\u4eba\u8bc4\u4ef7", "score": "8.5", "movie_name": "\u6a21\u4eff\u6e38\u620f", "ranking": "221"}
{"score_num": "93017\u4eba\u8bc4\u4ef7", "score": "8.6", "movie_name": "\u4e0a\u5e1d\u4e5f\u75af\u72c2", "ranking": "222"}
{"score_num": "266325\u4eba\u8bc4\u4ef7", "score": "8.3", "movie_name": "\u84dd\u8272\u5927\u95e8", "ranking": "223"}
{"score_num": "45693\u4eba\u8bc4\u4ef7", "score": "9.0", "movie_name": "\u7231\u00b7\u56de\u5bb6", "ranking": "224"}
{"score_num": "110077\u4eba\u8bc4\u4ef7", "score": "8.8", "movie_name": "\u7231\u5728\u5348\u591c\u964d\u4e34\u524d", "ranking": "225"}
{"score_num": "178237\u4eba\u8bc4\u4ef7", "score": "8.6", "movie_name": "\u65e0\u654c\u7834\u574f\u738b", "ranking": "226"}
{"score_num": "87075\u4eba\u8bc4\u4ef7", "score": "8.6", "movie_name": "\u5927\u536b\u00b7\u6208\u5c14\u7684\u4e00\u751f", "ranking": "227"}
{"score_num": "125194\u4eba\u8bc4\u4ef7", "score": "8.5", "movie_name": "\u8840\u94bb", "ranking": "228"}
{"score_num": "141076\u4eba\u8bc4\u4ef7", "score": "8.8", "movie_name": "\u623f\u95f4", "ranking": "229"}
{"score_num": "326177\u4eba\u8bc4\u4ef7", "score": "8.3", "movie_name": "\u56fd\u738b\u7684\u6f14\u8bb2", "ranking": "230"}
{"score_num": "95579\u4eba\u8bc4\u4ef7", "score": "8.6", "movie_name": "\u67aa\u706b", "ranking": "231"}
{"score_num": "298933\u4eba\u8bc4\u4ef7", "score": "8.2", "movie_name": "\u75af\u72c2\u7684\u77f3\u5934", "ranking": "232"}
{"score_num": "123338\u4eba\u8bc4\u4ef7", "score": "8.5", "movie_name": "\u9ea6\u515c\u6545\u4e8b", "ranking": "233"}
{"score_num": "197240\u4eba\u8bc4\u4ef7", "score": "8.3", "movie_name": "\u66fe\u7ecf", "ranking": "234"}
{"score_num": "139531\u4eba\u8bc4\u4ef7", "score": "8.4", "movie_name": "\u6696\u6696\u5185\u542b\u5149", "ranking": "235"}
{"score_num": "210538\u4eba\u8bc4\u4ef7", "score": "8.7", "movie_name": "\u5934\u8111\u7279\u5de5\u961f", "ranking": "236"}
{"score_num": "81131\u4eba\u8bc4\u4ef7", "score": "8.7", "movie_name": "\u5343\u94a7\u4e00\u53d1", "ranking": "237"}
{"score_num": "121274\u4eba\u8bc4\u4ef7", "score": "8.5", "movie_name": "\u9057\u613f\u6e05\u5355", "ranking": "238"}
{"score_num": "127417\u4eba\u8bc4\u4ef7", "score": "8.5", "movie_name": "\u8352\u5c9b\u4f59\u751f", "ranking": "239"}
{"score_num": "92842\u4eba\u8bc4\u4ef7", "score": "8.6", "movie_name": "\u8774\u8776", "ranking": "240"}
{"score_num": "102032\u4eba\u8bc4\u4ef7", "score": "8.6", "movie_name": "\u5df4\u9ece\u6dd8\u6c14\u5e2e", "ranking": "241"}
{"score_num": "54380\u4eba\u8bc4\u4ef7", "score": "8.9", "movie_name": "\u4e0e\u72fc\u5171\u821e", "ranking": "242"}
{"score_num": "138004\u4eba\u8bc4\u4ef7", "score": "8.5", "movie_name": "\u6708\u7403", "ranking": "243"}
{"score_num": "112300\u4eba\u8bc4\u4ef7", "score": "8.5", "movie_name": "\u5077\u62d0\u62a2\u9a97", "ranking": "244"}
{"score_num": "53337\u4eba\u8bc4\u4ef7", "score": "9.0", "movie_name": "\u6211\u7231\u4f60", "ranking": "245"}
{"score_num": "162760\u4eba\u8bc4\u4ef7", "score": "8.4", "movie_name": "\u5f57\u661f\u6765\u7684\u90a3\u4e00\u591c", "ranking": "246"}
{"score_num": "62390\u4eba\u8bc4\u4ef7", "score": "8.8", "movie_name": "\u6b65\u5c65\u4e0d\u505c", "ranking": "247"}
{"score_num": "78946\u4eba\u8bc4\u4ef7", "score": "8.8", "movie_name": "\u5bff\u53f8\u4e4b\u795e", "ranking": "248"}
{"score_num": "191456\u4eba\u8bc4\u4ef7", "score": "8.3", "movie_name": "\u591c\u8bbf\u5438\u8840\u9b3c", "ranking": "249"}
{"score_num": "94682\u4eba\u8bc4\u4ef7", "score": "8.6", "movie_name": "\u5eca\u6865\u9057\u68a6", "ranking": "250"}
